{
    "title": "Plesk",
    "description": "Next-Level server management platform",
    "type": "object",
    "properties": {
        "license": {
        "title": "Plesk Activation Key (Leave blank if not available)",
        "type": "string"
      },
      "domain": {
        "type": "string",
        "title": "Hostname"
      },
      "user": {
        "type": "string",
        "title": "Username",
        "default": "ElvisPlesky"
      },
      "rootmail": {
        "type": "string",
        "format": "email",
        "title": "Administrators Email"
      },
      "passwd": {
        "type": "string",
        "title": "Password",
        "minLenght": 5
      },
      "fail2ban": {
        "title": "Enable fail2ban",
        "type": "boolean",
        "oneOf": [
          {
            "title": "Yes",
            "const": true
          },
          {
            "title": "No",
            "const": false
          }
        ]
      },
      "letsencrypt": {
        "title": "Enable SSL with Let's Encrypt",
        "type": "boolean",
        "oneOf": [
          {
            "title": "Yes",
            "const": true
          },
          {
            "title": "No",
            "const": false
          }
        ]
      }
    },  "toggleMask": {
        "title": "Apply color mask",
        "$ref": "#/definitions/Toggle"
      }
  }